molecular_simulations/__init__.py
molecular_simulations/logging_config.py
molecular_simulations/analysis/__init__.py
molecular_simulations/analysis/autocluster.py
molecular_simulations/analysis/constant_pH_analysis.py
molecular_simulations/analysis/cov_ppi.py
molecular_simulations/analysis/fingerprinter.py
molecular_simulations/analysis/interaction_energy.py
molecular_simulations/analysis/ipSAE.py
molecular_simulations/analysis/sasa.py
molecular_simulations/analysis/utils.py
molecular_simulations/build/__init__.py
molecular_simulations/build/build_amber.py
molecular_simulations/build/build_calvados.py
molecular_simulations/build/build_interface.py
molecular_simulations/build/build_ligand.py
molecular_simulations/data/__init__.py
molecular_simulations/data/constant_ph_reference_energies.py
molecular_simulations/simulate/__init__.py
molecular_simulations/simulate/cph_simulation.py
molecular_simulations/simulate/free_energy.py
molecular_simulations/simulate/mmpbsa.py
molecular_simulations/simulate/multires_simulator.py
molecular_simulations/simulate/omm_simulator.py
molecular_simulations/simulate/reporters.py
molecular_simulations/simulate/constantph/constantph.py
molecular_simulations/simulate/constantph/logging.py
molecular_simulations/simulate/constantph/reference_energy.py
molecular_simulations/utils/__init__.py
molecular_simulations/utils/amber_utils.py
molecular_simulations/utils/mda_utils.py
molecular_simulations/utils/parsl_settings.py
molecular_simulations-0.4.1.dist-info/METADATA
molecular_simulations-0.4.1.dist-info/WHEEL
molecular_simulations-0.4.1.dist-info/licenses/LICENSE
molecular_simulations-0.4.1.dist-info/RECORD
