Metadata-Version: 2.4
Name: molecular_simulations
Version: 0.4.1
Summary: A small package for building molecular systems using the AMBER \ force field and deploying OpenMM simulations on HPC clusters using Parsl.
Project-URL: Homepage, https://github.com/msinclair-py/molecular-dynamics
Project-URL: Issues, https://github.com/msinclair-py/molecular-dynamics/issues
Author-email: Matt Sinclair <msinclair@anl.gov>
License-Expression: MIT
License-File: LICENSE
Classifier: Programming Language :: Python :: 3
Requires-Python: >=3.10
Requires-Dist: black-pdbfixer
Requires-Dist: mdanalysis>=2.7
Requires-Dist: mdtraj
Requires-Dist: natsort
Requires-Dist: numba
Requires-Dist: openmm>=8.0
Requires-Dist: parmed
Requires-Dist: parsl>=2024.1.29
Requires-Dist: polars
Requires-Dist: pydantic
Requires-Dist: pyyaml
Requires-Dist: rust-simulation-tools
Requires-Dist: scikit-learn
Requires-Dist: seaborn
Provides-Extra: dev
Requires-Dist: numpy>=1.22; extra == 'dev'
Requires-Dist: pytest-cov>=4.0; extra == 'dev'
Requires-Dist: pytest>=7.0; extra == 'dev'
Provides-Extra: docutils
Requires-Dist: docutils; extra == 'docutils'
Requires-Dist: sphinx; extra == 'docutils'
Requires-Dist: sphinx-rtd-theme; extra == 'docutils'
Requires-Dist: sphinx-wagtail-theme; extra == 'docutils'
Provides-Extra: ligand
Requires-Dist: openbabel; extra == 'ligand'
Requires-Dist: rdkit; extra == 'ligand'
